.coveragerc
.gitignore
.travis.yml
CHANGES.rst
CONTRIBUTORS.rst
MANIFEST.in
README.rst
bootstrap.py
buildout.cfg
setup.py
docs/LICENSE.GPL
docs/LICENSE.txt
src/transmogrify/__init__.py
src/transmogrify.wppolls.egg-info/PKG-INFO
src/transmogrify.wppolls.egg-info/SOURCES.txt
src/transmogrify.wppolls.egg-info/dependency_links.txt
src/transmogrify.wppolls.egg-info/entry_points.txt
src/transmogrify.wppolls.egg-info/namespace_packages.txt
src/transmogrify.wppolls.egg-info/not-zip-safe
src/transmogrify.wppolls.egg-info/requires.txt
src/transmogrify.wppolls.egg-info/top_level.txt
src/transmogrify/wppolls/__init__.py
src/transmogrify/wppolls/configure.zcml
src/transmogrify/wppolls/logger.py
src/transmogrify/wppolls/sections.py
src/transmogrify/wppolls/wppolls.cfg
src/transmogrify/wppolls/profiles/default/metadata.xml
src/transmogrify/wppolls/profiles/default/transmogrifier.txt
src/transmogrify/wppolls/tests/__init__.py