Metadata-Version: 1.1
Name: transmogrify.wppolls
Version: 1.0a1
Summary: Transmogrifier pipeline sections to import WordPress polls into Plone.
Home-page: https://github.com/collective/transmogrify.wppolls
Author: Héctor Velarde
Author-email: hecto.velarde@gmail.com
License: UNKNOWN
Keywords: import wordpress blog plone transmogrifier pipeline blueprint wxr
Platform: UNKNOWN
Classifier: Development Status :: 3 - Alpha
Classifier: Environment :: Web Environment
Classifier: Framework :: Plone
Classifier: Framework :: Plone :: 4.3
Classifier: Intended Audience :: System Administrators
Classifier: License :: OSI Approved :: GNU General Public License v2 (GPLv2)
Classifier: Operating System :: OS Independent
Classifier: Programming Language :: Python
Classifier: Programming Language :: Python :: 2.7
Classifier: Topic :: Software Development :: Libraries :: Python Modules
